[
  {
    "Ad_ID": 300001000000001,
    "Creative_ID": 300001000000001,
    "Account": "GoogleFlow",
    "Campaign": "Flow Generated Content",
    "Status": "ACTIVE",
    "Performance_Rating": "PENDING_ANALYSIS",
    "CPA": "TBD",
    "CVR": "TBD",
    "CTR": "TBD",
    "Spend": "0.00",
    "Purchases": "0",
    "Video_Views": "0",
    "Hook_Rate": "TBD",
    "Facebook_Preview_Link": "TBD",
    "Meta_Video_URL": "TBD",
    "Google_Drive_Download_Link": "TBD",
    "Google_Drive_View_Link": "TBD",
    "Creative_Type": "TBD",
    "Hook_Type": "TBD",
    "Targeting": "Broad",
    "Priority": "\ud83d\udd0d NEEDS_REVIEW",
    "Ad_Name": "video: Flow Generated / Video 1",
    "Notes": "Generated: 2025-06-24 | Flow Project Video 1 | Element Type: video",
    "Download_Command": "TBD"
  },
  {
    "Ad_ID": 300001000000002,
    "Creative_ID": 300001000000002,
    "Account": "GoogleFlow",
    "Campaign": "Flow Generated Content",
    "Status": "ACTIVE",
    "Performance_Rating": "PENDING_ANALYSIS",
    "CPA": "TBD",
    "CVR": "TBD",
    "CTR": "TBD",
    "Spend": "0.00",
    "Purchases": "0",
    "Video_Views": "0",
    "Hook_Rate": "TBD",
    "Facebook_Preview_Link": "TBD",
    "Meta_Video_URL": "TBD",
    "Google_Drive_Download_Link": "TBD",
    "Google_Drive_View_Link": "TBD",
    "Creative_Type": "TBD",
    "Hook_Type": "TBD",
    "Targeting": "Broad",
    "Priority": "\ud83d\udd0d NEEDS_REVIEW",
    "Ad_Name": "video: Flow Generated / Video 2",
    "Notes": "Generated: 2025-06-24 | Flow Project Video 2 | Element Type: video",
    "Download_Command": "TBD"
  },
  {
    "Ad_ID": 300001000000003,
    "Creative_ID": 300001000000003,
    "Account": "GoogleFlow",
    "Campaign": "Flow Generated Content",
    "Status": "ACTIVE",
    "Performance_Rating": "PENDING_ANALYSIS",
    "CPA": "TBD",
    "CVR": "TBD",
    "CTR": "TBD",
    "Spend": "0.00",
    "Purchases": "0",
    "Video_Views": "0",
    "Hook_Rate": "TBD",
    "Facebook_Preview_Link": "TBD",
    "Meta_Video_URL": "TBD",
    "Google_Drive_Download_Link": "TBD",
    "Google_Drive_View_Link": "TBD",
    "Creative_Type": "TBD",
    "Hook_Type": "TBD",
    "Targeting": "Broad",
    "Priority": "\ud83d\udd0d NEEDS_REVIEW",
    "Ad_Name": "video: Flow Generated / Video 3",
    "Notes": "Generated: 2025-06-24 | Flow Project Video 3 | Element Type: video",
    "Download_Command": "TBD"
  },
  {
    "Ad_ID": 300001000000004,
    "Creative_ID": 300001000000004,
    "Account": "GoogleFlow",
    "Campaign": "Flow Generated Content",
    "Status": "ACTIVE",
    "Performance_Rating": "PENDING_ANALYSIS",
    "CPA": "TBD",
    "CVR": "TBD",
    "CTR": "TBD",
    "Spend": "0.00",
    "Purchases": "0",
    "Video_Views": "0",
    "Hook_Rate": "TBD",
    "Facebook_Preview_Link": "TBD",
    "Meta_Video_URL": "TBD",
    "Google_Drive_Download_Link": "TBD",
    "Google_Drive_View_Link": "TBD",
    "Creative_Type": "TBD",
    "Hook_Type": "TBD",
    "Targeting": "Broad",
    "Priority": "\ud83d\udd0d NEEDS_REVIEW",
    "Ad_Name": "video: Flow Generated / Video 4",
    "Notes": "Generated: 2025-06-24 | Flow Project Video 4 | Element Type: video",
    "Download_Command": "TBD"
  }
]